Week4/2_1_Multiplexer.v
module mux2(
    input wire i0,
    input wire i1,
    input wire j,
    output wire o
);
    assign o = (j == 0) ? i0 : i1;
endmodule

Week4/2_1_Multiplexer_tb.v
module TB;
    reg A, B, S;
    wire X;

 
    mux2 newMUX(
        .i0(A),
        .i1(B),
        .j(S),
        .o(X)
    );

    initial begin
        $dumpfile("MUX2_test.vcd");
        $dumpvars(0, TB);
        $monitor("Time=%0t | S=%b | A=%b | B=%b | X=%b", $time, S, A, B, X);

        // Test all combinations
        A = 1'b0; B = 1'b0; S = 1'b0; #5;
        A = 1'b0; B = 1'b0; S = 1'b1; #5;
        A = 1'b0; B = 1'b1; S = 1'b0; #5;
        A = 1'b0; B = 1'b1; S = 1'b1; #5;
        A = 1'b1; B = 1'b0; S = 1'b0; #5;
        A = 1'b1; B = 1'b0; S = 1'b1; #5;
        A = 1'b1; B = 1'b1; S = 1'b0; #5;
        A = 1'b1; B = 1'b1; S = 1'b1; #5;

        $finish;
    end
endmodule

Week4/MUX2_test.vcd
$date
	Mon Sep 01 14:55:32 2025
$end
$version
	Icarus Verilog
$end
$timescale
	1s
$end
$scope module TB $end
$var wire 1 ! X $end
$var reg 1 " A $end
$var reg 1 # B $end
$var reg 1 $ S $end
$scope module newMUX $end
$var wire 1 % i0 $end
$var wire 1 & i1 $end
$var wire 1 ' j $end
$var wire 1 ! o $end
$upscope $end
$upscope $end
$enddefinitions $end
#0
$dumpvars
0'
0&
0%
0$
0#
0"
0!
$end
#5
1$
1'
#10
0$
0'
1#
1&
#15
1!
1$
1'
#20
0$
0'
0#
0&
1"
1%
#25
0!
1$
1'
#30
1!
0$
0'
1#
1&
#35
1$
1'
