Week3/1.v
module fulladd (
    input  wire a, b, cin,
    output wire sum, cout
);
    assign sum  = a ^ b ^ cin;
    assign cout = (a & b) | (b & cin) | (a & cin);
endmodule
module fulladdR (
    input  wire [3:0] a, b,
    input  wire       cin,
    output wire [3:0] sum,
    output wire       cout
);

wire [2:0] c;

fulladd u0 (a[0], b[0], cin,   sum[0], c[0]);
fulladd u1 (a[1], b[1], c[0],  sum[1], c[1]);
fulladd u2 (a[2], b[2], c[1],  sum[2], c[2]);
fulladd u3 (a[3], b[3], c[2],  sum[3], cout);

endmodule

Week3/1_tb.v

`timescale 1 ns / 100 ps 
`define TESTVECS 10 

module tb; 
    reg clk, reset; 
    reg [3:0] i0, i1; 
    reg cin; 
    wire [3:0] o; 
    wire cout; 
    reg [8:0] test_vecs[0:(`TESTVECS-1)]; 
    integer i; 
    initial begin 
        $dumpfile("rca_test.vcd"); 
        $dumpvars(0, tb); 
    end 
    initial begin 
        reset = 1'b1; 
        #12.5 reset = 1'b0; 
    end 
    initial clk = 1'b0; 
    always #5 clk = ~clk; 
    initial begin 
        test_vecs[0] = 9'b000000000; 
        test_vecs[1] = 9'b000000001;
        test_vecs[2] = 9'b000100010; 
        test_vecs[3] = 9'b000100011; 
        test_vecs[4] = 9'b001000100; 
        test_vecs[5] = 9'b101010110; 
        test_vecs[6] = 9'b101010111; 
        test_vecs[7] = 9'b110011010; 
        test_vecs[8] = 9'b111111100; 
        test_vecs[9] = 9'b111111101; 
    end 
    initial {i0, i1, cin, i} = 0; 
    fulladdR u0 ( i0, i1, cin, o, cout ); 
    initial begin 
        #6 
        for (i = 0; i < `TESTVECS; i = i + 1) begin 
            #10;
            {i0, i1, cin} = test_vecs[i]; 
        end 
        #100 $finish;
    end 
    always @(i0 or i1 or cin)
        $monitor( "At time = %t, i0=%b, i1=%b, cin=%b, Sum=%b, Carry=%b", $time, i0, i1, cin, o, cout );
endmodule

Week3/rca_test.vcd
$date
	Mon Aug 25 14:11:00 2025
$end
$version
	Icarus Verilog
$end
$timescale
	100ps
$end
$scope module tb $end
$var wire 1 ! cout $end
$var wire 4 " o [3:0] $end
$var reg 1 # cin $end
$var reg 1 $ clk $end
$var integer 32 % i [31:0] $end
$var reg 4 & i0 [3:0] $end
$var reg 4 ' i1 [3:0] $end
$var reg 1 ( reset $end
$scope module u0 $end
$var wire 4 ) a [3:0] $end
$var wire 4 * b [3:0] $end
$var wire 3 + c [2:0] $end
$var wire 1 , cin $end
$var wire 1 ! cout $end
$var wire 4 - sum [3:0] $end
$scope module u0 $end
$var wire 1 . a $end
$var wire 1 / b $end
$var wire 1 , cin $end
$var wire 1 0 cout $end
$var wire 1 1 sum $end
$upscope $end
$scope module u1 $end
$var wire 1 2 a $end
$var wire 1 3 b $end
$var wire 1 4 cin $end
$var wire 1 5 cout $end
$var wire 1 6 sum $end
$upscope $end
$scope module u2 $end
$var wire 1 7 a $end
$var wire 1 8 b $end
$var wire 1 9 cin $end
$var wire 1 : cout $end
$var wire 1 ; sum $end
$upscope $end
$scope module u3 $end
$var wire 1 < a $end
$var wire 1 = b $end
$var wire 1 > cin $end
$var wire 1 ! cout $end
$var wire 1 ? sum $end
$upscope $end
$upscope $end
$upscope $end
$enddefinitions $end
#0
$dumpvars
0?
0>
0=
0<
0;
0:
09
08
07
06
05
04
03
02
01
00
0/
0.
b0 -
0,
b0 +
b0 *
b0 )
1(
b0 '
b0 &
b0 %
0$
0#
b0 "
0!
$end
#50
1$
#100
0$
#125
0(
#150
1$
#160
b1 %
#200
0$
#250
1$
#260
11
b1 "
b1 -
b10 %
1#
1,
#300
0$
#350
1$
#360
16
14
10
b1 +
1.
1/
01
b10 "
b10 -
b11 %
b1 &
b1 )
b1 '
b1 *
0#
0,
#400
0$
#450
1$
#460
11
b11 "
b11 -
b100 %
1#
1,
#500
0$
#550
1$
#560
06
1;
04
19
00
15
b10 +
0.
12
0/
13
01
b100 "
b100 -
b101 %
b10 &
b10 )
b10 '
b10 *
0#
0,
#600
0$
#650
1$
#660
1!
11
b101 "
b101 -
1<
1/
1=
b110 %
b1010 &
b1010 )
b1011 '
b1011 *
#700
0$
#750
1$
#760
16
14
10
b11 +
01
b110 "
b110 -
b111 %
1#
1,
#800
0$
#850
1$
#860
0;
1?
06
09
1>
04
05
1:
00
b100 +
02
17
03
18
11
b1001 "
b1001 -
b1000 %
b1100 &
b1100 )
b1101 '
b1101 *
0#
0,
#900
0$
#950
1$
#960
1;
b1101 "
b1101 -
19
15
b110 +
1.
12
0/
13
b1001 %
b1111 &
b1111 )
b1110 '
b1110 *
#1000
0$
#1050
1$
#1060
16
14
10
b111 +
01
b1110 "
b1110 -
b1010 %
1#
1,
